EC/P1/P1_Diseño_ALU/mux2_1.v
// Práctica 1 E.C - Objetivo 2 (y 4), crear una celda lógica, FA, una Celda A.L
// y probarlas con su Test Bench
// Cristopher Manuel Afonso Mora - alu0101402031
// Como este archivo es dado por el profesorado, no lo he modificado y no
// le hago un test bench porque está bien

module mux2_1(output wire out, input wire a, input wire b, input wire s);

	assign out = s ? b : a; //oper. condicional de C, sintaxis [condicion ? valor_si_cierta : valor_si_falsa] 

endmodule

EC/P1/P1_Diseño_ALU/fa.v
// Práctica 1 E.C - Objetivo 2, crear una celda lógica, FA, una Celda A.L
// y probarlas con su Test Bench
// Cristopher Manuel Afonso Mora - alu0101402031

module fa(output wire cout, sum, input wire a, b, cin);
  assign {cout, sum} = a + b + cin;
endmodule

EC/P1/P1_Diseño_ALU/mux4_1.v
// Práctica 1 E.C - Objetivo 1, crear un mux4_1 y probarlo con un Test Bench
// Cristopher Manuel Afonso Mora - alu0101402031

// 1 Fichero / Modulo 
// Nombre igual que el modulo con extensión .v

// Module NombreMod(.......);
//...
//EndModule

//          out=.....;
//always @(...., ..., ...., ...)
//               variables
//begin
//....
//    out=...;
//....
//End
module mux4_1(output reg out, input wire a, b, c, d, input wire [1:0] s);
  always@(a or b or c or d or s)
  begin
    case(s)
      2'b00  : out = a;      //if s = 00, output is a
      2'b01  : out = b;      //if s = 01, output is b
      2'b10  : out = c;      //if s = 10, output is c
      2'b11  : out = d;      //if s = 11, output is d
      default: out = 2'bxx;  //if s = default, output is anything
    endcase
  end
endmodule

EC/P1/P1_Diseño_ALU/cl.v
// Práctica 1 E.C - Objetivo 2, crear una celda lógica, FA, una Celda A.L
// y probarlas con su Test Bench
// Cristopher Manuel Afonso Mora - alu0101402031

module cl(output wire out, input wire a, b, input wire [1:0] s);
  //Declaración de conexiones o variables internas:
  wire and_out, or_out, xor_out, not_out;
  //Estructura interna: Instancias de puertas y sus conexiones
  // las siguientes 4 líneas son una alternativa a la estructura interna del módulo
  // assign and_out = a & b;
  // assign or_out = a | b;
  // assign xor_out = a ^ b;
  // assign not_out = ~a;

  and and1(and_out, a, b);
  or or1(or_out, a, b);
  xor xor1(xor_out, a, b);
  not not1(not_out, a);
  mux4_1 mux_4_1(out, and_out, or_out, xor_out, not_out, s);
endmodule

EC/P1/P1_Diseño_ALU/cal.v
// Práctica 1 E.C - Objetivo 2, crear una celda lógica, FA, una Celda A.L
// y probarlas con su Test Bench
// Cristopher Manuel Afonso Mora - alu0101402031

module cal(output wire out, c_out, input wire a, b, arit, c_in, input wire [1:0] s);
  //Declaración de conexiones o variables internas:
  wire fa_out, cl_out;
  //Estructura interna: Instancias de puertas y sus conexiones
  cl cl1(cl_out, a, b, s);
  fa fa1(c_out, fa_out, a, b, c_in);
  mux2_1 mux2_1_1(out, cl_out, fa_out, arit);
endmodule

EC/P1/P1_Diseño_ALU/compl1.v
// Práctica 1 E.C - Objetivo 3, crear un módulo que complemente números de
// 4 bits en complemento a 1, y probarlo con su Test Bench
// Cristopher Manuel Afonso Mora - alu0101402031

module compl1(output wire [3:0] Sal, input wire [3:0] Ent, input wire cpl);
  assign Sal = cpl ? ~Ent : Ent;
endmodule

EC/P1/P1_Diseño_ALU/mux2_4.v
// Práctica 1 E.C - Objetivo 2 (y 4), crear una celda lógica, FA, una Celda A.L
// y probarlas con su Test Bench
// Cristopher Manuel Afonso Mora - alu0101402031
// Como este archivo es dado por el profesorado, no lo he modificado y no
// le hago un test bench porque está bien

module mux2_4(output wire [3:0] out, input wire [3:0] a, input wire [3:0] b, input wire s);

	assign out = s ? b : a; //oper. condicional de C, sintaxis [condicion ? valor_si_cierta : valor_si_falsa] 

endmodule

EC/P1/P1_Diseño_ALU/alu.v
// Práctica 1 E.C - Objetivo 4, crear el módulo ALU usando los bloques que ya
// he creado y probarlo con su Test Bench (dado por el profesor)
// Cristopher Manuel Afonso Mora - alu0101402031

module alu(output wire [3:0] R, output wire zero, carry, sign, input wire [3:0] A, B, input wire [1:0] ALUOp, input wire arit);
  //Declaración de conexiones o variables internas:
  reg [3:0] kZero = 4'b0000;
  wire [3:0] out_B, OP1, OP2;
  wire op1_A, op2_B, cpl, Cin0;
  wire Cout0, Cout1, Cout2;

  //Estructura interna: Instancias de puertas y sus conexiones

  // Objetivo 5, definir las señales que saldrán de la ALU
  assign zero = ~R[0] && ~R[1] && ~R[2] && ~R[3];
  assign sign = arit ? R[3] : 1'bx;

  // Objetivo 5, definir las señales internas que deciden el tipo de operación
  assign op1_A = ~arit || ~ALUOp[1];
  assign op2_B = ~arit || ~ALUOp[1] || ALUOp[0];
  assign cpl = arit && (ALUOp[1] || ALUOp[0]);
  assign Cin0 = ALUOp[1] || ALUOp[0];

  // Muxes y compl1 del objetivo 4
  mux2_4 mux2_4_A(OP1, kZero, A, op1_A);
  mux2_4 mux2_4_B(out_B, A, B, op2_B);
  compl1 compl1_B(OP2, out_B, cpl);

  // Celdas cal del objetivo 4
  cal cal0(R[0], Cout0, OP1[0], OP2[0], arit, Cin0, ALUOp);
  cal cal1(R[1], Cout1, OP1[1], OP2[1], arit, Cout0, ALUOp);
  cal cal2(R[2], Cout2, OP1[2], OP2[2], arit, Cout1, ALUOp);
  cal cal3(R[3], carry, OP1[3], OP2[3], arit, Cout2, ALUOp);
endmodule

EC/P1/P1_Diseño_ALU/alu_tb.v
// Testbench para modulo alu
`timescale 1 ns / 10 ps //Directiva que fija la unidad de tiempo de simulación y la precision de la unidad
module alu_tb;
//declaracion de señales
reg [1:0] t_Op;
reg t_arit;
reg [3:0] t_A, t_B;
wire [3:0] t_R;
wire t_z, t_c, t_s;
integer errores;
//instancia del modulo a testear
alu mat(t_R, t_z, t_c, t_s, t_A, t_B, t_Op, t_arit);

initial
begin
  $dumpfile("alu.vcd");
  $dumpvars;
/*  $monitor("tiempo=%0d A=%b B=%b L=%b Op=%b R=%b, Z=%b, C=%b, S=%b", $time, t_A, t_B, t_arit, t_Op, t_R, t_z, t_c, t_s);
*/
  errores = 0;
  t_arit = 1'b0;
  repeat(2)
	begin
	t_Op = 2'b0;
	repeat(4)
		begin
		  t_A = 4'b0;
		  repeat(16) 
		  begin
			t_B = 4'b0;
			repeat(16) 
			begin
				# 2 check;
				t_B = t_B + 1;
			end
			t_A = t_A + 1;
		  end
		  t_Op = t_Op + 1;
		end
		t_arit = t_arit + 1;
	end
	$display("Encontradas %d operaciones erroneas", errores);
  //fin simulacion
  $finish;
end

// Tarea para hacer la comprobación automática de resultados
task check;
reg [4:0] result;
reg flag_zero, flag_carry, flag_sign;
begin
	// Si las operaciones son lógicas
	if (t_arit)
	begin
		case (t_Op)
			2'b00: result = t_A + t_B;
			2'b01: result = t_A + ((t_B ^4'b1111) + 1);
			2'b10: result = (t_A ^4'b1111) + 4'b0001;
			2'b11: result = (t_B ^4'b1111) + 4'b0001;
			default: $display("ERROR. Valor no esperado para t_Op: %b", t_Op);
		endcase
		flag_carry = result[4];
		flag_sign = result[3];
		if (flag_sign !== t_s || flag_carry !== t_c)
		begin
			errores = errores + 1;
			$display("ERROR con operación L=%b, OP=%b A=%b B=%b", t_arit, t_Op, t_A, t_B);
			if (flag_sign !== t_s)
				$display("ERROR. Flag de signo esperado %b, obtenido %b", flag_sign, t_s);
			if (flag_carry !== t_c)
				$display("\tFlag de acarreo esperado %b, obtenido %b", flag_carry, t_c);
		end
	end
	else
	begin
		case (t_Op)
			2'b00: result[3:0] = t_A & t_B;
			2'b01: result[3:0] = t_A | t_B;
			2'b10: result[3:0] = t_A ^ t_B;
			2'b11: result[3:0] = ~t_A;
			default: $display("ERROR. Valor no esperado para t_Op: %b", t_Op);
		endcase
		flag_carry = 1'bx;
		flag_sign = 1'bx;
	end
	flag_zero = ~| result[3:0];
	if (result[3:0] !== t_R || flag_zero !== t_z)
	begin
		errores = errores + 1;
		$display("ERROR con operación L=%b, OP=%b A=%b B=%b", t_arit, t_Op, t_A, t_B);
		if (result[3:0] !== t_R)
			$display("\tResultado esperado %b, obtenido %b", result[3:0], t_R);
		if (flag_zero !== t_z)
			$display("\tFlag de cero esperado %b, obtenido %b", flag_zero, t_z);
	end
end
endtask
endmodule

EC/P1/P1_Diseño_ALU/alu.vcd
$date
	Mon Nov 15 11:08:16 2021
$end
$version
	Icarus Verilog
$end
$timescale
	10ps
$end
$scope module alu_tb $end
$var wire 1 ! t_z $end
$var wire 1 " t_s $end
$var wire 1 # t_c $end
$var wire 4 $ t_R [3:0] $end
$var reg 4 % t_A [3:0] $end
$var reg 4 & t_B [3:0] $end
$var reg 2 ' t_Op [1:0] $end
$var reg 1 ( t_arit $end
$var integer 32 ) errores [31:0] $end
$scope module mat $end
$var wire 4 * A [3:0] $end
$var wire 2 + ALUOp [1:0] $end
$var wire 4 , B [3:0] $end
$var wire 1 - Cin0 $end
$var wire 1 ( arit $end
$var wire 1 . cpl $end
$var wire 1 / op1_A $end
$var wire 1 0 op2_B $end
$var wire 1 ! zero $end
$var wire 1 " sign $end
$var wire 4 1 out_B [3:0] $end
$var wire 1 # carry $end
$var wire 4 2 R [3:0] $end
$var wire 4 3 OP2 [3:0] $end
$var wire 4 4 OP1 [3:0] $end
$var wire 1 5 Cout2 $end
$var wire 1 6 Cout1 $end
$var wire 1 7 Cout0 $end
$var reg 4 8 kZero [3:0] $end
$scope module cal0 $end
$var wire 1 9 a $end
$var wire 1 ( arit $end
$var wire 1 : b $end
$var wire 1 - c_in $end
$var wire 2 ; s [1:0] $end
$var wire 1 < out $end
$var wire 1 = fa_out $end
$var wire 1 > cl_out $end
$var wire 1 7 c_out $end
$scope module cl1 $end
$var wire 1 9 a $end
$var wire 1 ? and_out $end
$var wire 1 : b $end
$var wire 1 @ not_out $end
$var wire 1 A or_out $end
$var wire 2 B s [1:0] $end
$var wire 1 C xor_out $end
$var wire 1 > out $end
$scope module mux_4_1 $end
$var wire 1 ? a $end
$var wire 1 A b $end
$var wire 1 C c $end
$var wire 1 @ d $end
$var wire 2 D s [1:0] $end
$var reg 1 > out $end
$upscope $end
$upscope $end
$scope module fa1 $end
$var wire 1 9 a $end
$var wire 1 : b $end
$var wire 1 - cin $end
$var wire 1 = sum $end
$var wire 1 7 cout $end
$upscope $end
$scope module mux2_1_1 $end
$var wire 1 > a $end
$var wire 1 = b $end
$var wire 1 ( s $end
$var wire 1 < out $end
$upscope $end
$upscope $end
$scope module cal1 $end
$var wire 1 E a $end
$var wire 1 ( arit $end
$var wire 1 F b $end
$var wire 1 7 c_in $end
$var wire 2 G s [1:0] $end
$var wire 1 H out $end
$var wire 1 I fa_out $end
$var wire 1 J cl_out $end
$var wire 1 6 c_out $end
$scope module cl1 $end
$var wire 1 E a $end
$var wire 1 K and_out $end
$var wire 1 F b $end
$var wire 1 L not_out $end
$var wire 1 M or_out $end
$var wire 2 N s [1:0] $end
$var wire 1 O xor_out $end
$var wire 1 J out $end
$scope module mux_4_1 $end
$var wire 1 K a $end
$var wire 1 M b $end
$var wire 1 O c $end
$var wire 1 L d $end
$var wire 2 P s [1:0] $end
$var reg 1 J out $end
$upscope $end
$upscope $end
$scope module fa1 $end
$var wire 1 E a $end
$var wire 1 F b $end
$var wire 1 7 cin $end
$var wire 1 I sum $end
$var wire 1 6 cout $end
$upscope $end
$scope module mux2_1_1 $end
$var wire 1 J a $end
$var wire 1 I b $end
$var wire 1 ( s $end
$var wire 1 H out $end
$upscope $end
$upscope $end
$scope module cal2 $end
$var wire 1 Q a $end
$var wire 1 ( arit $end
$var wire 1 R b $end
$var wire 1 6 c_in $end
$var wire 2 S s [1:0] $end
$var wire 1 T out $end
$var wire 1 U fa_out $end
$var wire 1 V cl_out $end
$var wire 1 5 c_out $end
$scope module cl1 $end
$var wire 1 Q a $end
$var wire 1 W and_out $end
$var wire 1 R b $end
$var wire 1 X not_out $end
$var wire 1 Y or_out $end
$var wire 2 Z s [1:0] $end
$var wire 1 [ xor_out $end
$var wire 1 V out $end
$scope module mux_4_1 $end
$var wire 1 W a $end
$var wire 1 Y b $end
$var wire 1 [ c $end
$var wire 1 X d $end
$var wire 2 \ s [1:0] $end
$var reg 1 V out $end
$upscope $end
$upscope $end
$scope module fa1 $end
$var wire 1 Q a $end
$var wire 1 R b $end
$var wire 1 6 cin $end
$var wire 1 U sum $end
$var wire 1 5 cout $end
$upscope $end
$scope module mux2_1_1 $end
$var wire 1 V a $end
$var wire 1 U b $end
$var wire 1 ( s $end
$var wire 1 T out $end
$upscope $end
$upscope $end
$scope module cal3 $end
$var wire 1 ] a $end
$var wire 1 ( arit $end
$var wire 1 ^ b $end
$var wire 1 5 c_in $end
$var wire 2 _ s [1:0] $end
$var wire 1 ` out $end
$var wire 1 a fa_out $end
$var wire 1 b cl_out $end
$var wire 1 # c_out $end
$scope module cl1 $end
$var wire 1 ] a $end
$var wire 1 c and_out $end
$var wire 1 ^ b $end
$var wire 1 d not_out $end
$var wire 1 e or_out $end
$var wire 2 f s [1:0] $end
$var wire 1 g xor_out $end
$var wire 1 b out $end
$scope module mux_4_1 $end
$var wire 1 c a $end
$var wire 1 e b $end
$var wire 1 g c $end
$var wire 1 d d $end
$var wire 2 h s [1:0] $end
$var reg 1 b out $end
$upscope $end
$upscope $end
$scope module fa1 $end
$var wire 1 ] a $end
$var wire 1 ^ b $end
$var wire 1 5 cin $end
$var wire 1 a sum $end
$var wire 1 # cout $end
$upscope $end
$scope module mux2_1_1 $end
$var wire 1 b a $end
$var wire 1 a b $end
$var wire 1 ( s $end
$var wire 1 ` out $end
$upscope $end
$upscope $end
$scope module compl1_B $end
$var wire 1 . cpl $end
$var wire 4 i Sal [3:0] $end
$var wire 4 j Ent [3:0] $end
$upscope $end
$scope module mux2_4_A $end
$var wire 4 k a [3:0] $end
$var wire 4 l b [3:0] $end
$var wire 1 / s $end
$var wire 4 m out [3:0] $end
$upscope $end
$scope module mux2_4_B $end
$var wire 4 n a [3:0] $end
$var wire 4 o b [3:0] $end
$var wire 1 0 s $end
$var wire 4 p out [3:0] $end
$upscope $end
$upscope $end
$scope task check $end
$var reg 1 q flag_carry $end
$var reg 1 r flag_sign $end
$var reg 1 s flag_zero $end
$var reg 5 t result [4:0] $end
$upscope $end
$upscope $end
$enddefinitions $end
#0
$dumpvars
bx t
xs
xr
xq
b0 p
b0 o
b0 n
b0 m
b0 l
b0 k
b0 j
b0 i
b0 h
0g
b0 f
0e
1d
0c
0b
0a
0`
b0 _
0^
0]
b0 \
0[
b0 Z
0Y
1X
0W
0V
0U
0T
b0 S
0R
0Q
b0 P
0O
b0 N
0M
1L
0K
0J
0I
0H
b0 G
0F
0E
b0 D
0C
b0 B
0A
1@
0?
0>
0=
0<
b0 ;
0:
09
b0 8
07
06
05
b0 4
b0 3
b0 2
b0 1
10
1/
0.
0-
b0 ,
b0 +
b0 *
b0 )
0(
b0 '
b0 &
b0 %
b0 $
0#
x"
1!
$end
#200
1A
1C
1=
1:
b1 3
b1 i
b1 1
b1 j
b1 p
b1 &
b1 ,
b1 o
1s
bx0000 t
#400
1M
1O
1I
0A
0C
0=
1F
0:
b10 3
b10 i
b10 1
b10 j
b10 p
b10 &
b10 ,
b10 o
#600
1A
1C
1=
1:
b11 3
b11 i
b11 1
b11 j
b11 p
b11 &
b11 ,
b11 o
#800
1Y
1[
1U
0M
0O
0I
0A
0C
0=
1R
0F
0:
b100 3
b100 i
b100 1
b100 j
b100 p
b100 &
b100 ,
b100 o
#1000
1A
1C
1=
1:
b101 3
b101 i
b101 1
b101 j
b101 p
b101 &
b101 ,
b101 o
#1200
1M
1O
1I
0A
0C
0=
1F
0:
b110 3
b110 i
b110 1
b110 j
b110 p
b110 &
b110 ,
b110 o
#1400
1A
1C
1=
1:
b111 3
b111 i
b111 1
b111 j
b111 p
b111 &
b111 ,
b111 o
#1600
1e
1g
1a
0Y
0[
0U
0M
0O
0I
0A
0C
0=
1^
0R
0F
0:
b1000 3
b1000 i
b1000 1
b1000 j
b1000 p
b1000 &
b1000 ,
b1000 o
#1800
1A
1C
1=
1:
b1001 3
b1001 i
b1001 1
b1001 j
b1001 p
b1001 &
b1001 ,
b1001 o
#2000
1M
1O
1I
0A
0C
0=
1F
0:
b1010 3
b1010 i
b1010 1
b1010 j
b1010 p
b1010 &
b1010 ,
b1010 o
#2200
1A
1C
1=
1:
b1011 3
b1011 i
b1011 1
b1011 j
b1011 p
b1011 &
b1011 ,
b1011 o
#2400
1Y
1[
1U
0M
0O
0I
0A
0C
0=
1R
0F
0:
b1100 3
b1100 i
b1100 1
b1100 j
b1100 p
b1100 &
b1100 ,
b1100 o
#2600
1A
1C
1=
1:
b1101 3
b1101 i
b1101 1
b1101 j
b1101 p
b1101 &
b1101 ,
b1101 o
#2800
1M
1O
1I
0A
0C
0=
1F
0:
b1110 3
b1110 i
b1110 1
b1110 j
b1110 p
b1110 &
b1110 ,
b1110 o
#3000
1A
1C
1=
1:
b1111 3
b1111 i
b1111 1
b1111 j
b1111 p
b1111 &
b1111 ,
b1111 o
#3200
0e
0g
0a
0Y
0[
0U
0M
0O
0I
0@
0^
0R
0F
0:
19
b0 3
b0 i
b1 4
b1 m
b0 1
b0 j
b0 p
b1 %
b1 *
b1 l
b1 n
b0 &
b0 ,
b0 o
#3400
0!
b1 $
b1 2
1<
1>
1I
1?
0C
0=
17
1:
b1 3
b1 i
b1 1
b1 j
b1 p
b1 &
b1 ,
b1 o
#3600
1!
b0 $
b0 2
0<
0>
1M
1O
0?
1C
1=
07
1F
0:
b10 3
b10 i
b10 1
b10 j
b10 p
b10 &
b10 ,
b10 o
0s
bx0001 t
#3800
0!
b1 $
b1 2
1<
1U
1>
0I
16
1?
0C
0=
17
1:
b11 3
b11 i
b11 1
b11 j
b11 p
b11 &
b11 ,
b11 o
1s
bx0000 t
#4000
1!
b0 $
b0 2
0<
0>
1Y
1[
0M
0O
06
0?
1C
1=
07
1R
0F
0:
b100 3
b100 i
b100 1
b100 j
b100 p
b100 &
b100 ,
b100 o
0s
bx0001 t
#4200
0!
b1 $
b1 2
1<
1>
1I
1?
0C
0=
17
1:
b101 3
b101 i
b101 1
b101 j
b101 p
b101 &
b101 ,
b101 o
1s
bx0000 t
#4400
1!
b0 $
b0 2
0<
0>
1M
1O
0?
1C
1=
07
1F
0:
b110 3
b110 i
b110 1
b110 j
b110 p
b110 &
b110 ,
b110 o
0s
bx0001 t
#4600
0!
1a
b1 $
b1 2
1<
0U
15
1>
0I
16
1?
0C
0=
17
1:
b111 3
b111 i
b111 1
b111 j
b111 p
b111 &
b111 ,
b111 o
1s
bx0000 t
#4800
1!
b0 $
b0 2
0<
0>
1e
1g
0Y
0[
05
0M
0O
06
0?
1C
1=
07
1^
0R
0F
0:
b1000 3
b1000 i
b1000 1
b1000 j
b1000 p
b1000 &
b1000 ,
b1000 o
0s
bx0001 t
#5000
0!
b1 $
b1 2
1<
1>
1I
1?
0C
0=
17
1:
b1001 3
b1001 i
b1001 1
b1001 j
b1001 p
b1001 &
b1001 ,
b1001 o
1s
bx0000 t
#5200
1!
b0 $
b0 2
0<
0>
1M
1O
0?
1C
1=
07
1F
0:
b1010 3
b1010 i
b1010 1
b1010 j
b1010 p
b1010 &
b1010 ,
b1010 o
0s
bx0001 t
#5400
0!
b1 $
b1 2
1<
1U
1>
0I
16
1?
0C
0=
17
1:
b1011 3
b1011 i
b1011 1
b1011 j
b1011 p
b1011 &
b1011 ,
b1011 o
1s
bx0000 t
#5600
1!
b0 $
b0 2
0<
0>
1Y
1[
0M
0O
06
0?
1C
1=
07
1R
0F
0:
b1100 3
b1100 i
b1100 1
b1100 j
b1100 p
b1100 &
b1100 ,
b1100 o
0s
bx0001 t
#5800
0!
b1 $
b1 2
1<
1>
1I
1?
0C
0=
17
1:
b1101 3
b1101 i
b1101 1
b1101 j
b1101 p
b1101 &
b1101 ,
b1101 o
1s
bx0000 t
#6000
1!
b0 $
b0 2
0<
0>
1M
1O
0?
1C
1=
07
1F
0:
b1110 3
b1110 i
b1110 1
b1110 j
b1110 p
b1110 &
b1110 ,
b1110 o
0s
bx0001 t
#6200
0!
0a
1#
b1 $
b1 2
1<
0U
15
1>
0I
16
1?
0C
0=
17
1:
b1111 3
b1111 i
b1111 1
b1111 j
b1111 p
b1111 &
b1111 ,
b1111 o
1s
bx0000 t
#6400
1!
b0 $
b0 2
0<
0>
06
0e
0g
0#
0Y
0[
0U
05
0L
1I
0?
0A
1@
07
0^
0R
0F
0:
1E
09
b0 3
b0 i
b10 4
b10 m
b0 1
b0 j
b0 p
b10 %
b10 *
b10 l
b10 n
b0 &
b0 ,
b0 o
0s
bx0001 t
#6600
1A
1C
1=
1:
b1 3
b1 i
b1 1
b1 j
b1 p
b1 &
b1 ,
b1 o
1s
bx0000 t
#6800
0!
b10 $
b10 2
1H
1J
1U
1K
0O
0I
16
0A
0C
0=
1F
0:
b10 3
b10 i
b10 1
b10 j
b10 p
b10 &
b10 ,
b10 o
#7000
1A
1C
1=
1:
b11 3
b11 i
b11 1
b11 j
b11 p
b11 &
b11 ,
b11 o
0s
bx0010 t
#7200
1!
b0 $
b0 2
0H
0J
1Y
1[
0K
1O
1I
06
0A
0C
0=
1R
0F
0:
b100 3
b100 i
b100 1
b100 j
b100 p
b100 &
b100 ,
b100 o
#7400
1A
1C
1=
1:
b101 3
b101 i
b101 1
b101 j
b101 p
b101 &
b101 ,
b101 o
1s
bx0000 t
#7600
0!
b10 $
b10 2
1H
1a
1J
0U
15
1K
0O
0I
16
0A
0C
0=
1F
0:
b110 3
b110 i
b110 1
b110 j
b110 p
b110 &
b110 ,
b110 o
#7800
1A
1C
1=
1:
b111 3
b111 i
b111 1
b111 j
b111 p
b111 &
b111 ,
b111 o
0s
bx0010 t
#8000
1!
b0 $
b0 2
0H
0J
1e
1g
0Y
0[
05
0K
1O
1I
06
0A
0C
0=
1^
0R
0F
0:
b1000 3
b1000 i
b1000 1
b1000 j
b1000 p
b1000 &
b1000 ,
b1000 o
#8200
1A
1C
1=
1:
b1001 3
b1001 i
b1001 1
b1001 j
b1001 p
b1001 &
b1001 ,
b1001 o
1s
bx0000 t
#8400
0!
b10 $
b10 2
1H
1J
1U
1K
0O
0I
16
0A
0C
0=
1F
0:
b1010 3
b1010 i
b1010 1
b1010 j
b1010 p
b1010 &
b1010 ,
b1010 o
#8600
1A
1C
1=
1:
b1011 3
b1011 i
b1011 1
b1011 j
b1011 p
b1011 &
b1011 ,
b1011 o
0s
bx0010 t
#8800
1!
b0 $
b0 2
0H
0J
1Y
1[
0K
1O
1I
06
0A
0C
0=
1R
0F
0:
b1100 3
b1100 i
b1100 1
b1100 j
b1100 p
b1100 &
b1100 ,
b1100 o
#9000
1A
1C
1=
1:
b1101 3
b1101 i
b1101 1
b1101 j
b1101 p
b1101 &
b1101 ,
b1101 o
1s
bx0000 t
#9200
0!
b10 $
b10 2
1H
0a
1#
1J
0U
15
1K
0O
0I
16
0A
0C
0=
1F
0:
b1110 3
b1110 i
b1110 1
b1110 j
b1110 p
b1110 &
b1110 ,
b1110 o
#9400
1A
1C
1=
1:
b1111 3
b1111 i
b1111 1
b1111 j
b1111 p
b1111 &
b1111 ,
b1111 o
0s
bx0010 t
#9600
1!
b0 $
b0 2
0H
0J
0e
0g
0#
0Y
0[
05
0K
1O
1I
06
0@
0^
0R
0F
0:
19
b0 3
b0 i
b11 4
b11 m
b0 1
b0 j
b0 p
b11 %
b11 *
b11 l
b11 n
b0 &
b0 ,
b0 o
#9800
0!
b1 $
b1 2
1<
1U
1>
0I
16
1?
0C
0=
17
1:
b1 3
b1 i
b1 1
b1 j
b1 p
b1 &
b1 ,
b1 o
1s
bx0000 t
#10000
1H
b10 $
b10 2
0<
1J
0>
1K
0O
0?
1C
1=
07
1F
0:
b10 3
b10 i
b10 1
b10 j
b10 p
b10 &
b10 ,
b10 o
0s
bx0001 t
#10200
b11 $
b11 2
1<
1>
1I
1?
0C
0=
17
1:
b11 3
b11 i
b11 1
b11 j
b11 p
b11 &
b11 ,
b11 o
bx0010 t
#10400
1!
0H
b0 $
b0 2
0<
0a
0J
0>
06
1Y
1[
1U
05
0K
1O
0?
1C
1=
07
1R
0F
0:
b100 3
b100 i
b100 1
b100 j
b100 p
b100 &
b100 ,
b100 o
bx0011 t
#10600
0!
1a
b1 $
b1 2
1<
0U
15
1>
0I
16
1?
0C
0=
17
1:
b101 3
b101 i
b101 1
b101 j
b101 p
b101 &
b101 ,
b101 o
1s
bx0000 t
#10800
1H
b10 $
b10 2
0<
1J
0>
1K
0O
0?
1C
1=
07
1F
0:
b110 3
b110 i
b110 1
b110 j
b110 p
b110 &
b110 ,
b110 o
0s
bx0001 t
#11000
b11 $
b11 2
1<
1>
1I
1?
0C
0=
17
1:
b111 3
b111 i
b111 1
b111 j
b111 p
b111 &
b111 ,
b111 o
bx0010 t
#11200
1!
0H
b0 $
b0 2
0<
0J
0>
06
1e
1g
0Y
0[
0U
05
0K
1O
0?
1C
1=
07
1^
0R
0F
0:
b1000 3
b1000 i
b1000 1
b1000 j
b1000 p
b1000 &
b1000 ,
b1000 o
bx0011 t
#11400
0!
b1 $
b1 2
1<
1U
1>
0I
16
1?
0C
0=
17
1:
b1001 3
b1001 i
b1001 1
b1001 j
b1001 p
b1001 &
b1001 ,
b1001 o
1s
bx0000 t
#11600
1H
b10 $
b10 2
0<
1J
0>
1K
0O
0?
1C
1=
07
1F
0:
b1010 3
b1010 i
b1010 1
b1010 j
b1010 p
b1010 &
b1010 ,
b1010 o
0s
bx0001 t
#11800
b11 $
b11 2
1<
1>
1I
1?
0C
0=
17
1:
b1011 3
b1011 i
b1011 1
b1011 j
b1011 p
b1011 &
b1011 ,
b1011 o
bx0010 t
#12000
1!
0H
b0 $
b0 2
0<
1a
0#
0J
0>
06
1Y
1[
1U
05
0K
1O
0?
1C
1=
07
1R
0F
0:
b1100 3
b1100 i
b1100 1
b1100 j
b1100 p
b1100 &
b1100 ,
b1100 o
bx0011 t
#12200
0!
0a
1#
b1 $
b1 2
1<
0U
15
1>
0I
16
1?
0C
0=
17
1:
b1101 3
b1101 i
b1101 1
b1101 j
b1101 p
b1101 &
b1101 ,
b1101 o
1s
bx0000 t
#12400
1H
b10 $
b10 2
0<
1J
0>
1K
0O
0?
1C
1=
07
1F
0:
b1110 3
b1110 i
b1110 1
b1110 j
b1110 p
b1110 &
b1110 ,
b1110 o
0s
bx0001 t
#12600
b11 $
b11 2
1<
1>
1I
1?
0C
0=
17
1:
b1111 3
b1111 i
b1111 1
b1111 j
b1111 p
b1111 &
b1111 ,
b1111 o
bx0010 t
#12800
1!
0H
b0 $
b0 2
0<
1U
05
0J
0>
0e
0g
0a
0#
06
0X
0K
0M
1L
0I
0?
0A
1@
07
0^
0R
0F
0:
1Q
0E
09
b0 3
b0 i
b100 4
b100 m
b0 1
b0 j
b0 p
b100 %
b100 *
b100 l
b100 n
b0 &
b0 ,
b0 o
bx0011 t
#13000
1A
1C
1=
1:
b1 3
b1 i
b1 1
b1 j
b1 p
b1 &
b1 ,
b1 o
1s
bx0000 t
#13200
1M
1O
1I
0A
0C
0=
1F
0:
b10 3
b10 i
b10 1
b10 j
b10 p
b10 &
b10 ,
b10 o
#13400
1A
1C
1=
1:
b11 3
b11 i
b11 1
b11 j
b11 p
b11 &
b11 ,
b11 o
#13600
0!
b100 $
b100 2
1T
1V
1a
1W
0[
0U
15
0M
0O
0I
0A
0C
0=
1R
0F
0:
b100 3
b100 i
b100 1
b100 j
b100 p
b100 &
b100 ,
b100 o
#13800
1A
1C
1=
1:
b101 3
b101 i
b101 1
b101 j
b101 p
b101 &
b101 ,
b101 o
0s
bx0100 t
#14000
1M
1O
1I
0A
0C
0=
1F
0:
b110 3
b110 i
b110 1
b110 j
b110 p
b110 &
b110 ,
b110 o
#14200
1A
1C
1=
1:
b111 3
b111 i
b111 1
b111 j
b111 p
b111 &
b111 ,
b111 o
#14400
1!
b0 $
b0 2
0T
0V
1e
1g
0W
1[
1U
05
0M
0O
0I
0A
0C
0=
1^
0R
0F
0:
b1000 3
b1000 i
b1000 1
b1000 j
b1000 p
b1000 &
b1000 ,
b1000 o
#14600
1A
1C
1=
1:
b1001 3
b1001 i
b1001 1
b1001 j
b1001 p
b1001 &
b1001 ,
b1001 o
1s
bx0000 t
#14800
1M
1O
1I
0A
0C
0=
1F
0:
b1010 3
b1010 i
b1010 1
b1010 j
b1010 p
b1010 &
b1010 ,
b1010 o
#15000
1A
1C
1=
1:
b1011 3
b1011 i
b1011 1
b1011 j
b1011 p
b1011 &
b1011 ,
b1011 o
#15200
0!
b100 $
b100 2
1T
1V
0a
1#
1W
0[
0U
15
0M
0O
0I
0A
0C
0=
1R
0F
0:
b1100 3
b1100 i
b1100 1
b1100 j
b1100 p
b1100 &
b1100 ,
b1100 o
#15400
1A
1C
1=
1:
b1101 3
b1101 i
b1101 1
b1101 j
b1101 p
b1101 &
b1101 ,
b1101 o
0s
bx0100 t
#15600
1M
1O
1I
0A
0C
0=
1F
0:
b1110 3
b1110 i
b1110 1
b1110 j
b1110 p
b1110 &
b1110 ,
b1110 o
#15800
1A
1C
1=
1:
b1111 3
b1111 i
b1111 1
b1111 j
b1111 p
b1111 &
b1111 ,
b1111 o
#16000
1!
b0 $
b0 2
0T
0V
0e
0g
0#
0W
1[
1U
05
0M
0O
0I
0@
0^
0R
0F
0:
19
b0 3
b0 i
b101 4
b101 m
b0 1
b0 j
b0 p
b101 %
b101 *
b101 l
b101 n
b0 &
b0 ,
b0 o
#16200
0!
b1 $
b1 2
1<
1>
1I
1?
0C
0=
17
1:
b1 3
b1 i
b1 1
b1 j
b1 p
b1 &
b1 ,
b1 o
1s
bx0000 t
